device_protocol_sdk/__init__.py
device_protocol_sdk/abstract_device.py
device_protocol_sdk/device_pb2.py
device_protocol_sdk/device_pb2_grpc.py
device_protocol_sdk/pusher.py
device_protocol_sdk/model/__init__.py
device_protocol_sdk/model/action_item.py
device_protocol_sdk/model/device_key.py
device_protocol_sdk/model/device_status.py
device_protocol_sdk-1.2.5.dist-info/METADATA
device_protocol_sdk-1.2.5.dist-info/WHEEL
device_protocol_sdk-1.2.5.dist-info/top_level.txt
device_protocol_sdk-1.2.5.dist-info/RECORD
