Metadata-Version: 2.1
Name: device_protocol_sdk
Version: 1.2.5
Summary: 无人设备协议开发SDK
Author: fuhl
Requires-Python: >=3.8
Requires-Dist: grpcio >=1.48.2
Requires-Dist: grpcio-tools >=1.48.2
Requires-Dist: paho-mqtt >=1.6.1
Requires-Dist: pydantic >=1.9.0
Requires-Dist: websockets >=10.0
Requires-Dist: shapely >=2.1.2
